build_scripts/__init__.py
build_scripts/_common.py
build_scripts/_cuda.py
build_scripts/_utils.py
build_scripts/build_3rd.py
build_scripts/commands.py
build_scripts/ext_gtrace.py
build_scripts/ext_libgwatch_binding.py
build_scripts/ext_libgwatch_capsule.py
build_scripts/ext_libgwatch_instrumentation.py
build_scripts/ext_libgwatch_profiler.py
build_scripts/ext_libgwatch_scheduler.py
gwatch/__init__.py
gwatch/config.py
gwatch/libcgwatch.so
gwatch/libgwatch_capsule_hijack.so
gwatch/libgwatch_dark.so
gwatch/libgwatch_instrumentation.so
gwatch/libgwatch_scheduler.so
gwatch/libpygwatch.so
gwatch/libsqlite3.so
gwatch/assets/cuda/meta.json
gwatch/assets/cuda/sm80.bin
gwatch/assets/cuda/sm90a.bin
gwatch/bin/gwatch_profiler_exe
gwatch/capsule/__init__.py
gwatch/capsule/event.py
gwatch/capsule/metric.py
gwatch/capsule/torch_adaptor.py
gwatch/capsule/trace.py
gwatch/cuda/__init__.py
gwatch/cuda/assemble/__init__.py
gwatch/cuda/assemble/kernel_def_sass.py
gwatch/cuda/binary/__init__.py
gwatch/cuda/binary/cubin.py
gwatch/cuda/binary/fatbin.py
gwatch/cuda/binary/ptx.py
gwatch/cuda/binary/utils.py
gwatch/cuda/profile/__init__.py
gwatch/cuda/profile/context.py
gwatch/cuda/profile/device.py
gwatch/cuda/profile/profiler.py
gwatch/libs/libcgwatch.so
gwatch/libs/libgwatch_capsule_hijack.so
gwatch/libs/libgwatch_dark.so
gwatch/libs/libgwatch_instrumentation.so
gwatch/libs/libsqlite3.so
gwatch/scheduler/__init__.py
gwatch/scheduler/__main__.py
gwatch/scheduler/scheduler.py
gwatch-0.0.2.dist-info/METADATA
gwatch-0.0.2.dist-info/WHEEL
gwatch-0.0.2.dist-info/top_level.txt
gwatch-0.0.2.dist-info/RECORD
