Metadata-Version: 2.1
Name: gwatch
Version: 0.0.2
Summary: G-Watch is a toolbox for GPU profiling and program analysis.
Home-page: https://github.com/G-Watch/G-Watch
Author: Zhuobin Huang
Author-email: zhuobin@u.nus.edu
Classifier: Programming Language :: Python :: 3
Classifier: License :: OSI Approved :: MIT License
Classifier: Operating System :: OS Independent
Requires-Python: >=3.7
